{
  "results": [
    {
      "product_name": "Ai+ Pulse",
      "colour": "Black",
      "ram_rom": "4 GB + 64 GB",
      "model_id": "41211",
      "amazon_links": [
        {
          "url": "https://www.amazon.in/sspa/click?ie=UTF8&spc=MTo4MjE2NDAyMjU2Mzc5MTQ6MTc1NjcxOTM2ODpzcF9hdGY6MzAwNTk3NTMzNDE1NjMyOjowOjo&url=%2FLava-Titanium-Dimensity-Processor-Supports%2Fdp%2FB0FB437XS2%2Fref%3Dsr_1_1_sspa%3Fcrid%3D20QNFN7D2D1PG%26dib%3DeyJ2IjoiMSJ9.KwdM80iu80czVY_uKwLdds0qTBClgEeScUC7p5hVZMHGjHj071QN20LucGBJIEps.XZ21lf_PjUs9NhRicydfdQUrIyr01CLj-QQzQ8ztnus%26dib_tag%3Dse%26keywords%3DAi%252B%2BPulse%2BBlack%2B4%2BGB%2B%252B%2B64%2BGB%26nsdOptOutParam%3Dtrue%26qid%3D1756719368%26sprefix%3Dai%252B%2Bpulse%2Bblack%2B4%2Bgb%2B%252B%2B64%2Bgb%252Caps%252C409%26sr%3D8-1-spons%26sp_csd%3Dd2lkZ2V0TmFtZT1zcF9hdGY%26psc%3D1&aref=6KCnv15Kuc&sp_cr=ZAZ",
          "product_name_via_url": "Lava Storm Lite 5G (Cosmic Titanium, 4+4*GB RAM, 64GB Storage) | India's First MTK Dimensity 6400 Processor | 50MP AI Camera | IP64 Rated | 120 Hz Display | 5000 mAh Battery | Supports All 5G Bands"
        },
        {
          "url": "https://www.amazon.in/AI-Pulse-Black-64GB-Storage/dp/B0FK2RZT8B/ref=sr_1_2?crid=20QNFN7D2D1PG&dib=eyJ2IjoiMSJ9.KwdM80iu80czVY_uKwLdds0qTBClgEeScUC7p5hVZMHGjHj071QN20LucGBJIEps.XZ21lf_PjUs9NhRicydfdQUrIyr01CLj-QQzQ8ztnus&dib_tag=se&keywords=Ai%2B+Pulse+Black+4+GB+%2B+64+GB&nsdOptOutParam=true&qid=1756719368&sprefix=ai%2B+pulse+black+4+gb+%2B+64+gb%2Caps%2C409&sr=8-2",
          "product_name_via_url": "AI+ Pulse 4G (Black, 4GB RAM, 64GB Storage)"
        },
        {
          "url": "https://www.amazon.in/realme-Obsidian-6300mAh-Segments-Biggest/dp/B0FG2LPC6K/ref=sr_1_3?crid=20QNFN7D2D1PG&dib=eyJ2IjoiMSJ9.KwdM80iu80czVY_uKwLdds0qTBClgEeScUC7p5hVZMHGjHj071QN20LucGBJIEps.XZ21lf_PjUs9NhRicydfdQUrIyr01CLj-QQzQ8ztnus&dib_tag=se&keywords=Ai%2B+Pulse+Black+4+GB+%2B+64+GB&nsdOptOutParam=true&qid=1756719368&sprefix=ai%2B+pulse+black+4+gb+%2B+64+gb%2Caps%2C409&sr=8-3",
          "product_name_via_url": "realme NARZO 80 Lite 4G (Obsidian Black, 4GB+64GB) | 6300mAh Segment's Biggest Battery | 7.94mm Slim Design | 300% Ultra Volume | Pulse Light: 9 Colors, 5 Glow Modes | Ai Assist"
        },
        {
          "url": "https://www.amazon.in/realme-6300mAh-Segments-Biggest-Battery/dp/B0FG2NBVBN/ref=sr_1_4?crid=20QNFN7D2D1PG&dib=eyJ2IjoiMSJ9.KwdM80iu80czVY_uKwLdds0qTBClgEeScUC7p5hVZMHGjHj071QN20LucGBJIEps.XZ21lf_PjUs9NhRicydfdQUrIyr01CLj-QQzQ8ztnus&dib_tag=se&keywords=Ai%2B+Pulse+Black+4+GB+%2B+64+GB&nsdOptOutParam=true&qid=1756719368&sprefix=ai%2B+pulse+black+4+gb+%2B+64+gb%2Caps%2C409&sr=8-4",
          "product_name_via_url": "realme NARZO 80 Lite 4G (Beach Gold, 4GB+64GB) | 6300mAh Segment's Biggest Battery | 7.94mm Slim Design | 300% Ultra Volume | Pulse Light: 9 Colors, 5 Glow Modes | Ai Assist"
        },
        {
          "url": "https://www.amazon.in/sspa/click?ie=UTF8&spc=MTo0NTI0NzAyMDIxOTExOTc5OjE3NTY3MTkzNjg6c3Bfc2VhcmNoX3RoZW1hdGljOjMwMDQzMjg4OTM5MTIzMjo6MDo6&url=%2FLava-O3-Glossy-GB-Charging%2Fdp%2FB0DP911BW3%2Fref%3Dsxin_14_pa_sp_search_thematic_sspa%3Fcontent-id%3Damzn1.sym.739e670d-dfb3-4be0-9815-d8c5c0372e07%253Aamzn1.sym.739e670d-dfb3-4be0-9815-d8c5c0372e07%26crid%3D20QNFN7D2D1PG%26cv_ct_cx%3DAi%252B%2BPulse%2BBlack%2B4%2BGB%2B%252B%2B64%2BGB%26keywords%3DAi%252B%2BPulse%2BBlack%2B4%2BGB%2B%252B%2B64%2BGB%26nsdOptOutParam%3Dtrue%26pd_rd_i%3DB0DP911BW3%26pd_rd_r%3Daaebd5e1-56d9-47cb-a1f9-70c5212a433d%26pd_rd_w%3DWTmK0%26pd_rd_wg%3DKkMuq%26pf_rd_p%3D739e670d-dfb3-4be0-9815-d8c5c0372e07%26pf_rd_r%3DQ72D2MM9E8R39XAVMEDE%26qid%3D1756719368%26sbo%3DRZvfv%252F%252FHxDF%252BO5021pAnSA%253D%253D%26sprefix%3Dai%252B%2Bpulse%2Bblack%2B4%2Bgb%2B%252B%2B64%2Bgb%252Caps%252C409%26sr%3D1-1-66673dcf-083f-43ba-b782-d4a436cc5cfb-spons%26sp_csd%3Dd2lkZ2V0TmFtZT1zcF9zZWFyY2hfdGhlbWF0aWM%26psc%3D1&sp_cr=ZAZ",
          "product_name_via_url": "O3 Pro (Glossy Black, 4 GB RAM, 128 GB Storage)| Bigger 6.56\" HD+ Display | 50 MP AI Triple Rear Camera | 8 MP Front Camera| 5000 mAh Battery | 10W Charging | Charger in Box"
        }
      ]
    },
    {
      "product_name": "Ai+ Pulse",
      "colour": "Black",
      "ram_rom": "6 GB + 128 GB",
      "model_id": "41211",
      "amazon_links": [
        {
          "url": "https://www.amazon.in/realme-Obsidian-6300mAh-Segments-Biggest/dp/B0FG2PFMG2/ref=sr_1_1?crid=JE5DYB40YCYS&dib=eyJ2IjoiMSJ9.YqgXwKIY_EADtLv5rGV2pqgTOQVzhgQ42QLuAjv0vZs.2_xg4jFGq8MZPLDaaniE118eWKgRjrXd1EfkSZFLZ4k&dib_tag=se&keywords=Ai%2B+Pulse+Black+6+GB+%2B+128+GB&nsdOptOutParam=true&qid=1756719387&sprefix=ai%2B+pulse+black+6+gb+%2B+128+gb%2Caps%2C261&sr=8-1",
          "product_name_via_url": "realme NARZO 80 Lite 4G (Obsidian Black, 6GB+128GB) | 6300mAh Segment's Biggest Battery | 7.94mm Slim Design | 300% Ultra Volume | Pulse Light: 9 Colors, 5 Glow Modes | Ai Assist"
        },
        {
          "url": "https://www.amazon.in/AI-Pulse-Black-64GB-Storage/dp/B0FK2RZT8B/ref=sr_1_2?crid=JE5DYB40YCYS&dib=eyJ2IjoiMSJ9.YqgXwKIY_EADtLv5rGV2pqgTOQVzhgQ42QLuAjv0vZs.2_xg4jFGq8MZPLDaaniE118eWKgRjrXd1EfkSZFLZ4k&dib_tag=se&keywords=Ai%2B+Pulse+Black+6+GB+%2B+128+GB&nsdOptOutParam=true&qid=1756719387&sprefix=ai%2B+pulse+black+6+gb+%2B+128+gb%2Caps%2C261&sr=8-2",
          "product_name_via_url": "AI+ Pulse 4G (Black, 4GB RAM, 64GB Storage)"
        },
        {
          "url": "https://www.amazon.in/sspa/click?ie=UTF8&spc=MTo3MjUxMDA2MDUxNTExOTM6MTc1NjcxOTM4NzpzcF9tdGY6MzAwNTc4MTk3MzMyNDMyOjowOjo&url=%2FLava-Bold-N1-Pro-Titanium%2Fdp%2FB0F1Z3QTM8%2Fref%3Dsr_1_3_sspa%3Fcrid%3DJE5DYB40YCYS%26dib%3DeyJ2IjoiMSJ9.YqgXwKIY_EADtLv5rGV2pqgTOQVzhgQ42QLuAjv0vZs.2_xg4jFGq8MZPLDaaniE118eWKgRjrXd1EfkSZFLZ4k%26dib_tag%3Dse%26keywords%3DAi%252B%2BPulse%2BBlack%2B6%2BGB%2B%252B%2B128%2BGB%26nsdOptOutParam%3Dtrue%26qid%3D1756719387%26sprefix%3Dai%252B%2Bpulse%2Bblack%2B6%2Bgb%2B%252B%2B128%2Bgb%252Caps%252C261%26sr%3D8-3-spons%26sp_csd%3Dd2lkZ2V0TmFtZT1zcF9tdGY%26psc%3D1&aref=YrrilaDHJx&sp_cr=ZAZ",
          "product_name_via_url": "Lava Bold N1 Pro (Titanium Gold, 4 GB RAM, 128 GB Storage)| Bigger 6.67\" HD+ IP54 Display | 120 Hz Refresh Rate | 50 MP AI Triple Rear Camera | 8 MP Front Camera| 5000 mAh Battery | Charger in Box"
        },
        {
          "url": "https://www.amazon.in/sspa/click?ie=UTF8&spc=MTo3MjUxMDA2MDUxNTExOTM6MTc1NjcxOTM4NzpzcF9tdGY6MzAwNTk3NTYzNDU4NzMyOjowOjo&url=%2FLava-Storage-Dimensity-Processor-Supports%2Fdp%2FB0FB42K578%2Fref%3Dsr_1_4_sspa%3Fcrid%3DJE5DYB40YCYS%26dib%3DeyJ2IjoiMSJ9.YqgXwKIY_EADtLv5rGV2pqgTOQVzhgQ42QLuAjv0vZs.2_xg4jFGq8MZPLDaaniE118eWKgRjrXd1EfkSZFLZ4k%26dib_tag%3Dse%26keywords%3DAi%252B%2BPulse%2BBlack%2B6%2BGB%2B%252B%2B128%2BGB%26nsdOptOutParam%3Dtrue%26qid%3D1756719387%26sprefix%3Dai%252B%2Bpulse%2Bblack%2B6%2Bgb%2B%252B%2B128%2Bgb%252Caps%252C261%26sr%3D8-4-spons%26sp_csd%3Dd2lkZ2V0TmFtZT1zcF9tdGY%26psc%3D1&aref=MbjMRNcCk9&sp_cr=ZAZ",
          "product_name_via_url": "Lava Storm Lite 5G (Astral Blue, 4+4*GB RAM, 64GB Storage) | India's First MTK Dimensity 6400 Processor | 50MP AI Camera | IP64 Rated | 120 Hz Display | 5000mAh Battery | Supports All 5G Bands"
        },
        {
          "url": "https://www.amazon.in/sspa/click?ie=UTF8&spc=MToxMDI3NzA1NDMxMTMwNTA0OjE3NTY3MTkzODc6c3Bfc2VhcmNoX3RoZW1hdGljOjMwMDU5NzU2MzQ1ODczMjo6MDo6&url=%2FLava-Storage-Dimensity-Processor-Supports%2Fdp%2FB0FB42K578%2Fref%3Dsxin_14_pa_sp_search_thematic_sspa%3Fcontent-id%3Damzn1.sym.739e670d-dfb3-4be0-9815-d8c5c0372e07%253Aamzn1.sym.739e670d-dfb3-4be0-9815-d8c5c0372e07%26crid%3DJE5DYB40YCYS%26cv_ct_cx%3DAi%252B%2BPulse%2BBlack%2B6%2BGB%2B%252B%2B128%2BGB%26keywords%3DAi%252B%2BPulse%2BBlack%2B6%2BGB%2B%252B%2B128%2BGB%26nsdOptOutParam%3Dtrue%26pd_rd_i%3DB0FB42K578%26pd_rd_r%3Dce733f3c-1a74-451f-824f-c24a8115f0db%26pd_rd_w%3DMv1dE%26pd_rd_wg%3DY91Ey%26pf_rd_p%3D739e670d-dfb3-4be0-9815-d8c5c0372e07%26pf_rd_r%3D5ZYS97V8377TYWVTXE7Z%26qid%3D1756719387%26sbo%3DRZvfv%252F%252FHxDF%252BO5021pAnSA%253D%253D%26sprefix%3Dai%252B%2Bpulse%2Bblack%2B6%2Bgb%2B%252B%2B128%2Bgb%252Caps%252C261%26sr%3D1-1-66673dcf-083f-43ba-b782-d4a436cc5cfb-spons%26sp_csd%3Dd2lkZ2V0TmFtZT1zcF9zZWFyY2hfdGhlbWF0aWM%26psc%3D1&sp_cr=ZAZ",
          "product_name_via_url": "Lava Storm Lite 5G (Astral Blue, 4+4*GB RAM, 64GB Storage) | India's First MTK Dimensity 6400 Processor | 50MP AI Camera | IP64 Rated | 120 Hz Display | 5000mAh Battery | Supports All 5G Bands"
        }
      ]
    },
    {
      "product_name": "Ai+ Pulse",
      "colour": "Blue",
      "ram_rom": "4 GB + 64 GB",
      "model_id": "41211",
      "amazon_links": [
        {
          "url": "https://www.amazon.in/AI-Pulse-Black-64GB-Storage/dp/B0FK2RZT8B/ref=sr_1_1?crid=2PX8MP5K9R38B&dib=eyJ2IjoiMSJ9.vUzmKqSeZisBsyPx3uqarg.Cs5HpYrODWNib02hztlRqvanlC8AgCMAt2jH_LrRo1g&dib_tag=se&keywords=Ai%2B+Pulse+Blue+4+GB+%2B+64+GB&nsdOptOutParam=true&qid=1756719406&sprefix=ai%2B+pulse+blue+4+gb+%2B+64+gb%2Caps%2C198&sr=8-1",
          "product_name_via_url": "AI+ Pulse 4G (Black, 4GB RAM, 64GB Storage)"
        },
        {
          "url": "https://www.amazon.in/sspa/click?ie=UTF8&spc=MToyOTQwNzk0MTYwODc0NTE5OjE3NTY3MTk0MDY6c3BfbXRmOjMwMDU3ODE5NzMzMjQzMjo6MDo6&url=%2FLava-Bold-N1-Pro-Titanium%2Fdp%2FB0F1Z3QTM8%2Fref%3Dsr_1_2_sspa%3Fcrid%3D2PX8MP5K9R38B%26dib%3DeyJ2IjoiMSJ9.vUzmKqSeZisBsyPx3uqarg.Cs5HpYrODWNib02hztlRqvanlC8AgCMAt2jH_LrRo1g%26dib_tag%3Dse%26keywords%3DAi%252B%2BPulse%2BBlue%2B4%2BGB%2B%252B%2B64%2BGB%26nsdOptOutParam%3Dtrue%26qid%3D1756719406%26sprefix%3Dai%252B%2Bpulse%2Bblue%2B4%2Bgb%2B%252B%2B64%2Bgb%252Caps%252C198%26sr%3D8-2-spons%26sp_csd%3Dd2lkZ2V0TmFtZT1zcF9tdGY%26psc%3D1&aref=YrrilaDHJx&sp_cr=ZAZ",
          "product_name_via_url": "Lava Bold N1 Pro (Titanium Gold, 4 GB RAM, 128 GB Storage)| Bigger 6.67\" HD+ IP54 Display | 120 Hz Refresh Rate | 50 MP AI Triple Rear Camera | 8 MP Front Camera| 5000 mAh Battery | Charger in Box"
        },
        {
          "url": "https://www.amazon.in/sspa/click?ie=UTF8&spc=MToyOTQwNzk0MTYwODc0NTE5OjE3NTY3MTk0MDY6c3BfbXRmOjMwMDU5NzUzMzQxNTYzMjo6MDo6&url=%2FLava-Titanium-Dimensity-Processor-Supports%2Fdp%2FB0FB437XS2%2Fref%3Dsr_1_3_sspa%3Fcrid%3D2PX8MP5K9R38B%26dib%3DeyJ2IjoiMSJ9.vUzmKqSeZisBsyPx3uqarg.Cs5HpYrODWNib02hztlRqvanlC8AgCMAt2jH_LrRo1g%26dib_tag%3Dse%26keywords%3DAi%252B%2BPulse%2BBlue%2B4%2BGB%2B%252B%2B64%2BGB%26nsdOptOutParam%3Dtrue%26qid%3D1756719406%26sprefix%3Dai%252B%2Bpulse%2Bblue%2B4%2Bgb%2B%252B%2B64%2Bgb%252Caps%252C198%26sr%3D8-3-spons%26sp_csd%3Dd2lkZ2V0TmFtZT1zcF9tdGY%26psc%3D1&aref=6KCnv15Kuc&sp_cr=ZAZ",
          "product_name_via_url": "Lava Storm Lite 5G (Cosmic Titanium, 4+4*GB RAM, 64GB Storage) | India's First MTK Dimensity 6400 Processor | 50MP AI Camera | IP64 Rated | 120 Hz Display | 5000 mAh Battery | Supports All 5G Bands"
        },
        {
          "url": "https://www.amazon.in/sspa/click?ie=UTF8&spc=MToyOTQwNzk0MTYwODc0NTE5OjE3NTY3MTk0MDY6c3BfYnRmOjMwMDY0MDQ5OTMyNzgzMjo6MDo6&url=%2FLava-Shark-5G-Octacore-Processor%2Fdp%2FB0F945QD5Z%2Fref%3Dsr_1_4_sspa%3Fcrid%3D2PX8MP5K9R38B%26dib%3DeyJ2IjoiMSJ9.vUzmKqSeZisBsyPx3uqarg.Cs5HpYrODWNib02hztlRqvanlC8AgCMAt2jH_LrRo1g%26dib_tag%3Dse%26keywords%3DAi%252B%2BPulse%2BBlue%2B4%2BGB%2B%252B%2B64%2BGB%26nsdOptOutParam%3Dtrue%26qid%3D1756719406%26sprefix%3Dai%252B%2Bpulse%2Bblue%2B4%2Bgb%2B%252B%2B64%2Bgb%252Caps%252C198%26sr%3D8-4-spons%26sp_csd%3Dd2lkZ2V0TmFtZT1zcF9idGY%26psc%3D1&aref=XPZZBtKUGy&sp_cr=ZAZ",
          "product_name_via_url": "Lava Shark 5G (Steller Blue, 4GB RAM, 64GB Storage) |Bigger 6.75\" HD+ Notch Display | Octacore 5G Processor | 13 MP AI Camera |5000 mAh Battery| IP54 Rated Dust & Water Splash Proof"
        },
        {
          "url": "https://aax-eu-zaz.amazon.in/x/c/JNae7X63I7Rc_fyYeNYYDvcAAAGZBKLfBgoAAAH2AQBvbm9fdHhuX2JpZDEgICBvbm9fdHhuX2ltcDIgICBk8SAl/clv1_CEuOPUxokZA0iHrVA_9y3yzKS3JnfKhk8rUHqWWK-MQk138VwRSVBf018HHz9hvVjq0yzpNb3X7OfU16AmcAXlA8Ky-LHcjvPVNcIGNxFwKhE6EtokfB8IkGXCR_U-W6XJeXalC7rdIQEQQ8kV_3ZVhXLA8QC8x8H15tWbp4Xgyay_2WjkwrSxutOI2vKbYuDzUcfMyagcpNBHhtJZhsefQQh8yliMIIKin6O61_zAYOsoJhkeWuV2gvjBmW5lJBN2PMN-SRnR9AjX0lL9xFahCwdXiTzSjwM7id9b7_arUQIGal1aK1xkuNcA7FBIOT3_cq0eVrbNPflr7pJ6K4Jvdm5LtuBgM0qPM92cxuNrZy710gXhSo_yWr3JYqfnqDdhxLjmecuEw9thDIC-mtdkYBfLrRzPFNRvEpCWV2jTxgFe1_kgdoI2VpwpV6JHIFG-OwWsjgsrOtXiM7DjCZpKEWf0ms2mCYQTtgTbV7n9mGD0dk7s2izRPtS0xNFricmfda3FxGEYwynzuAh0-5yQODWwRmcmo6djaNSR6rH7DofgKiPz1B7kQPBXjrdEHsefg0kPl-VBmGjLx6pM0NATfcADpCyR1V8u8umKazrWoovLyO4a4ZPXHk5F3eTZyUFmEaTc0_BDZj7M15DYFthBMc2In7LTBtWHowqs5s46UzfmkOViGRqk5BhWngXsJ38BYR6HEw4soL6colCHWXLWMDzoj4bMnw9PjmC3cJKS7i3DapddJW7xhb29oPSf-tuKhNGCPDjknV7BO4C3zvJRNiqTjUCExQsMBHVOQLRAqN-FNzaLd7tBxlk8-KTWmYUuCBeFBA0jWTv-d5e5F9vLmztXMjhfyILr25of6rrUOg1ETPznEa9CbKhGCcpgGhtuovkuA7pHrEFeEiau49OfWB4cyl_zdwKSc6UCXQmnHYkQBLHUYsXHFCUCm3sG6jojyfdtzWwYy888PM_TWKZb4WB9WdILH732KbVCt8Au4VHTNtYxV-dLWM6x_jY1kgAjy33rBW7jFvZ4gA8bqrzx5jtyRJUcuYiExf8JlikCJRR2S8apGNGQb_WatcItx4UViqROCXGjU9HZy6Wo-knee7fw3AxIx9KJA5MSVyDIiINEScIfhgomN6DaGpv9jVjt8pdN66kwxWAtthgAQjSw06eOXbB3PiT9E9ga_lnrOPzyyR1lj9t4wdhClFJ_gSL1e7KG3h1kygQyotmFb8EtqGzcB3pJ1h2Cih8LJdGFXZC10YVkO8xTG5hBQQHav9RqEqldGxVkfZTIVmbJsdiU8t-LRgjrPi_xaiuWWsC7WvXeowb5nk5NI_nAaz8qM7PrAPVg2jwWPym9MWU0UV5_Hgzd49p05xcdpfZMJSsq4vnESVHlmWueiqPyWWWYdKMgTgflOrSBXMQitGaLOHN5yUoxy1NlBImJIy-tr3mD4fTjB6zIEoPMw1Hh_fbzCQ13Y_OHjqsoa4jzvqCSnXSW3M_xCQR_Ac0Z0h9Pc-5GlxrFrKJFKqal4k7ocpmdiH32X6awtNf-xGPbDebIY3Awjit-PZLUuuFX2wDagYu8Kq2ce-z7aEOp1gLtcrq8VEX8LOCFTozrXbRNXtOkguYR1T38vtzaUY-IXF917c_efPcFztZAilrzAKn2JAR4y4SDrnLUvJyoJLD0-8tj55lvwTSgXUa0EIIatVidI-XqqXOO0UgYveHXkK8-mnodi-iuhRXLKYu0F_vWWqk5UnHh3q-QsGsCyYsINGExiA82eJj9Lk_OotbZFF4EuVTvwl7ZMyyim4ku9BNcJQQ59J21YKFszH3XLRYaqHJCaPn4a6SLuGyr4L4vgnQP6Gg8BFsF4aZtFsEatpotznGH3JKIqXj4VNc_iRetxxaQdyiCJ_ivX_F6-9giJ-doOoydEgqOTYdykHgPWJjDcRGRH9OPbjmwVwosoHcbv2gI4blHABNyxV4rjodpkOxCnAFRJz-870PBvuvgk5puVOqytqv-2z9Rz5h84r5NN2roQRzvIiVTZjMd27GseHwEeg6ihhWI4hDVRLQM8PoE1-jr2Z8sP-ifZwZM7jQPAvdYF7VqJ0xZZEPEEHe_M5wzAjH5TS8nwCawMmT9DiPWzIGya7KW83HoTjg56WDopm8EYOCfa5Rf1YaQyWWJYNhoM2pwaYWiU5gCAeHksdKy--Ig4qjl1Df-rLrBo8tlr1JJRbaLcNN8fFUZUXaYI9SRvyC_sgEghDuLSXVqM8AVs/https://www.amazon.in/Sahyog-Wellness-Fingertip-Saturation-Respiratory/dp/B0842TV6TF/ref=sxbs_sbv_search_btf?content-id=amzn1.sym.fa654091-9aaa-43a3-ac17-a2ad95526fd2%3Aamzn1.sym.fa654091-9aaa-43a3-ac17-a2ad95526fd2&crid=2PX8MP5K9R38B&cv_ct_cx=Ai%2B+Pulse+Blue+4+GB+%2B+64+GB&keywords=Ai%2B+Pulse+Blue+4+GB+%2B+64+GB&nsdOptOutParam=true&pd_rd_i=B0842TV6TF&pd_rd_r=09cf48cd-f29b-451d-b465-476d5f3d44b5&pd_rd_w=hC9rc&pd_rd_wg=5KWMn&pf_rd_p=fa654091-9aaa-43a3-ac17-a2ad95526fd2&pf_rd_r=2SB7QETNYYXAKMJHC5H3&qid=1756719406&sbo=RZvfv%2F%2FHxDF%2BO5021pAnSA%3D%3D&sprefix=ai%2B+pulse+blue+4+gb+%2B+64+gb%2Caps%2C198&sr=1-1-f1821008-9dea-4812-b2b6-4a6e4a4f2d55",
          "product_name_via_url": "Sahyog Wellness Fingertip advanced OLED Type Pulse Oximeter measures Oxygen Saturation, Pulse Rate (SpO2), Perfusion Index & Respiratory Rate with Battery (Black)"
        }
      ]
    }
  ],
  "last_processed_index": 2,
  "timestamp": "2025-09-01T15:06:51.651940"
}